pi_anwing_webthing/__init__.py
pi_anwing_webthing/anwing.py
pi_anwing_webthing/anwing_thing.py
pi_anwing_webthing/motor_tb6612Fng.py
pi_anwing_webthing/switch.py
pi_anwing_webthing/unit.py
pi_anwing_webthing-0.1.3.dist-info/LICENSE
pi_anwing_webthing-0.1.3.dist-info/METADATA
pi_anwing_webthing-0.1.3.dist-info/WHEEL
pi_anwing_webthing-0.1.3.dist-info/entry_points.txt
pi_anwing_webthing-0.1.3.dist-info/top_level.txt
pi_anwing_webthing-0.1.3.dist-info/RECORD
