Metadata-Version: 2.1
Name: pi-anwing-webthing
Version: 0.1.3
Summary: A web connected patio awnings controller on Raspberry Pi
Home-page: https://github.com/grro/pi_anwing_webthing
Author: Gregor Roth
Author-email: gregor.roth@web.de
License: MIT
Keywords: webthings,anwing,control,pation,terrace
Platform: UNKNOWN
Classifier: Programming Language :: Python :: 3
Classifier: License :: OSI Approved :: Apache Software License
Classifier: Operating System :: OS Independent
Classifier: Development Status :: 3 - Alpha
Requires-Dist: webthing
Requires-Dist: schedule
Requires-Dist: RPi.GPIO
